LICENSE
MANIFEST.in
README.md
setup.py
testingwithnewplan/__init__.py
testingwithnewplan/api_helper.py
testingwithnewplan/configuration.py
testingwithnewplan/decorators.py
testingwithnewplan/testingwithnewplan_client.py
testingwithnewplan.egg-info/PKG-INFO
testingwithnewplan.egg-info/SOURCES.txt
testingwithnewplan.egg-info/dependency_links.txt
testingwithnewplan.egg-info/requires.txt
testingwithnewplan.egg-info/top_level.txt
testingwithnewplan/controllers/__init__.py
testingwithnewplan/controllers/base_controller.py
testingwithnewplan/controllers/pet_controller.py
testingwithnewplan/controllers/store_controller.py
testingwithnewplan/controllers/user_controller.py
testingwithnewplan/exceptions/__init__.py
testingwithnewplan/exceptions/api_exception.py
testingwithnewplan/http/__init__.py
testingwithnewplan/http/http_call_back.py
testingwithnewplan/http/http_client.py
testingwithnewplan/http/http_context.py
testingwithnewplan/http/http_method_enum.py
testingwithnewplan/http/http_request.py
testingwithnewplan/http/http_response.py
testingwithnewplan/http/requests_client.py
testingwithnewplan/models/__init__.py
testingwithnewplan/models/api_response.py
testingwithnewplan/models/category.py
testingwithnewplan/models/o_auth_scope_enum.py
testingwithnewplan/models/order.py
testingwithnewplan/models/pet.py
testingwithnewplan/models/status_1_enum.py
testingwithnewplan/models/status_2_enum.py
testingwithnewplan/models/status_enum.py
testingwithnewplan/models/tag.py
testingwithnewplan/models/user.py